setup.py
adb/__init__.py
adb/adb_commands.py
adb/adb_debug.py
adb/adb_protocol.py
adb/common.py
adb/common_cli.py
adb/fastboot.py
adb/fastboot_debug.py
adb/filesync_protocol.py
adb/sign_m2crypto.py
adb/sign_pythonrsa.py
adb/usb_exceptions.py
adb3.egg-info/PKG-INFO
adb3.egg-info/SOURCES.txt
adb3.egg-info/dependency_links.txt
adb3.egg-info/requires.txt
adb3.egg-info/top_level.txt