Metadata-Version: 1.1
Name: adb3
Version: 1.1.0
Summary: 
